byteapp_ak/__init__.py
byteapp_ak/datasets.py
byteapp_ak/exceptions.py
byteapp_ak/request.py
byteapp_ak/air/__init__.py
byteapp_ak/air/air_hebei.py
byteapp_ak/air/air_zhenqi.py
byteapp_ak/air/cons.py
byteapp_ak/air/crypto.js
byteapp_ak/air/outcrypto.js
byteapp_ak/air/sunrise_tad.py
byteapp_ak/article/__init__.py
byteapp_ak/article/cons.py
byteapp_ak/article/epu_index.py
byteapp_ak/article/ff_factor.py
byteapp_ak/article/fred_md.py
byteapp_ak/article/risk_rv.py
byteapp_ak/bank/__init__.py
byteapp_ak/bank/bank_cbirc_2020.py
byteapp_ak/bank/cons.py
byteapp_ak/bond/__init__.py
byteapp_ak/bond/bond_cb_sina.py
byteapp_ak/bond/bond_cb_ths.py
byteapp_ak/bond/bond_cbond.py
byteapp_ak/bond/bond_china.py
byteapp_ak/bond/bond_china_money.py
byteapp_ak/bond/bond_convert.py
byteapp_ak/bond/bond_em.py
byteapp_ak/bond/bond_info_cm.py
byteapp_ak/bond/bond_investing.py
byteapp_ak/bond/bond_issue_cninfo.py
byteapp_ak/bond/bond_nafmii.py
byteapp_ak/bond/bond_summary.py
byteapp_ak/bond/bond_zh_cov.py
byteapp_ak/bond/bond_zh_sina.py
byteapp_ak/bond/cons.py
byteapp_ak/cost/__init__.py
byteapp_ak/cost/cost_living.py
byteapp_ak/crypto/__init__.py
byteapp_ak/crypto/crypto_bitcoin_cme.py
byteapp_ak/crypto/crypto_hist_investing.py
byteapp_ak/crypto/crypto_hold.py
byteapp_ak/currency/__init__.py
byteapp_ak/currency/currency.py
byteapp_ak/currency/currency_china_bank_sina.py
byteapp_ak/currency/currency_safe.py
byteapp_ak/data/__init__.py
byteapp_ak/data/cninfo.js
byteapp_ak/data/crypto_info.zip
byteapp_ak/data/ths.js
byteapp_ak/economic/__init__.py
byteapp_ak/economic/cons.py
byteapp_ak/economic/macro_australia.py
byteapp_ak/economic/macro_bank.py
byteapp_ak/economic/macro_canada.py
byteapp_ak/economic/macro_china.py
byteapp_ak/economic/macro_china_hk.py
byteapp_ak/economic/macro_china_nbs.py
byteapp_ak/economic/macro_constitute.py
byteapp_ak/economic/macro_euro.py
byteapp_ak/economic/macro_finance_ths.py
byteapp_ak/economic/macro_germany.py
byteapp_ak/economic/macro_info_ws.py
byteapp_ak-1.15.7.1.1.1.dist-info/LICENSE
byteapp_ak-1.15.7.1.1.1.dist-info/METADATA
byteapp_ak-1.15.7.1.1.1.dist-info/WHEEL
byteapp_ak-1.15.7.1.1.1.dist-info/top_level.txt
byteapp_ak-1.15.7.1.1.1.dist-info/RECORD
